fabric/__init__.py
fabric/functions/__init__.py
fabric/functions/cosmos/__init__.py
fabric/functions/cosmos/client_registration.py
fabric/functions/cosmos/cosmos_client_provider.py
fabric/functions/cosmosdb/__init__.py
fabric/functions/cosmosdb/helpers.py
fabric/functions/fabric_app.py
fabric/functions/fabric_class.py
fabric/functions/fabric_item.py
fabric/functions/generic_audience_types.py
fabric/functions/keyvault/__init__.py
fabric/functions/keyvault/keyvault_client.py
fabric/functions/keyvault/keyvault_provider.py
fabric/functions/keyvault/keyvault_registration.py
fabric/functions/providers/__init__.py
fabric/functions/providers/base_fabricitem_provider.py
fabric/functions/udf_exception.py
fabric/functions/user_data_functions.py
fabric/internal/__init__.py
fabric/internal/arrow/__init__.py
fabric/internal/arrow/arrow_dataframe_response.py
fabric/internal/arrow/arrow_request.py
fabric/internal/arrow/arrow_series_response.py
fabric/internal/converters/__init__.py
fabric/internal/converters/basic_datatype_converter.py
fabric/internal/custom_token_credential.py
fabric/internal/decorators/__init__.py
fabric/internal/decorators/add_parameters.py
fabric/internal/decorators/add_timeout.py
fabric/internal/decorators/configure_fabric_function_builder.py
fabric/internal/decorators/constants.py
fabric/internal/decorators/ensure_formatted_returntype.py
fabric/internal/decorators/function_parameter_keywords.py
fabric/internal/decorators/log_error.py
fabric/internal/decorators/remove_unused_binding_params.py
fabric/internal/fabric_lakehouse_files_client.py
fabric/internal/invoke_response.py
fabric/internal/item_binding.py
fabric/internal/lib_helpers/__init__.py
fabric/internal/lib_helpers/module_factory.py
fabric/internal/logging/__init__.py
fabric/internal/logging/udf_logger.py
fabric/internal/middleware/__init__.py
fabric/internal/middleware/_invocationIdMiddleware/__init__.py
fabric/internal/openapi_spec_generator.py
fabric/internal/providers/__init__.py
fabric_user_data_functions-1.0.54.dist-info/LICENSE.md
fabric_user_data_functions-1.0.54.dist-info/METADATA
fabric_user_data_functions-1.0.54.dist-info/WHEEL
fabric_user_data_functions-1.0.54.dist-info/RECORD
